aup3/__init__.py
aup3/aup3.py
aup3/project.py
aup3/xml.py
aup3-1.0.1.dist-info/licenses/LICENSE
aup3-1.0.1.dist-info/METADATA
aup3-1.0.1.dist-info/WHEEL
aup3-1.0.1.dist-info/top_level.txt
aup3-1.0.1.dist-info/RECORD
