Metadata-Version: 2.4
Name: aup3
Version: 1.0.1
Summary: Pure python parser for Audacity project files
Author-email: Alba Mendez <me@alba.sh>
License-Expression: MIT
Project-URL: Homepage, https://github.com/mildsunrise/py-aup3
Project-URL: Issues, https://github.com/mildsunrise/py-aup3/issues
Classifier: Programming Language :: Python :: 3
Classifier: Operating System :: OS Independent
Requires-Python: >=3.9
License-File: LICENSE
Dynamic: license-file
